arp_llm/__init__.py
arp_llm/errors.py
arp_llm/json_utils.py
arp_llm/py.typed
arp_llm/settings.py
arp_llm/types.py
arp_llm/providers/__init__.py
arp_llm/providers/dev_mock.py
arp_llm/providers/openai.py
arp_llm-0.1.1.dist-info/licenses/LICENSE
arp_llm-0.1.1.dist-info/METADATA
arp_llm-0.1.1.dist-info/WHEEL
arp_llm-0.1.1.dist-info/top_level.txt
arp_llm-0.1.1.dist-info/RECORD
