Metadata-Version: 2.4
Name: arp-llm
Version: 0.1.1
Summary: Shared helper for calling LLM providers across the ARP/JARVIS stack.
Author: Agent Runtime Protocol
License-Expression: MIT
Requires-Python: >=3.11
License-File: LICENSE
Requires-Dist: openai>=2.14.0
Provides-Extra: schema
Requires-Dist: jsonschema>=4.23.0; extra == "schema"
Provides-Extra: dev
Requires-Dist: pyright>=1.1.0; extra == "dev"
Requires-Dist: pytest>=7; extra == "dev"
Requires-Dist: pytest-cov>=4; extra == "dev"
Requires-Dist: httpx>=0.27.0; extra == "dev"
Requires-Dist: jsonschema>=4.23.0; extra == "dev"
Dynamic: license-file
